pygrab/__init__.py
pygrab/exceptions.py
pygrab/js_scraper.py
pygrab/pygrab.py
pygrab/session.py
pygrab/tor.py
pygrab/warning.py
pygrab-3.1.6.dist-info/METADATA
pygrab-3.1.6.dist-info/WHEEL
pygrab-3.1.6.dist-info/RECORD
