Metadata-Version: 2.1
Name: pygrab
Version: 3.1.6
Summary: High level, performant HTTP library with out-of-the-box support for concurrency and Tor
License: MIT
Author: Anish Kanthamneni
Author-email: akneni@gmail.com
Requires-Python: >=3.8,<4.0
Classifier: License :: OSI Approved :: MIT License
Classifier: Programming Language :: Python :: 3
Classifier: Programming Language :: Python :: 3.8
Classifier: Programming Language :: Python :: 3.9
Classifier: Programming Language :: Python :: 3.10
Classifier: Programming Language :: Python :: 3.11
Classifier: Programming Language :: Python :: 3.12
Classifier: Programming Language :: Python :: 3.13
Requires-Dist: nest-asyncio (>=1.6.0,<2.0.0)
Requires-Dist: pygrab-ll (>=0.1.0,<0.2.0)
Requires-Dist: pyppeteer (>=2.0.0,<3.0.0)
Requires-Dist: pysocks (>=1.7.1,<2.0.0)
Requires-Dist: requests (>=2.32.3,<3.0.0)
